cintay/__init__.py
cintay/cintay.py
cintay-0.1.dist-info/LICENSE
cintay-0.1.dist-info/METADATA
cintay-0.1.dist-info/WHEEL
cintay-0.1.dist-info/top_level.txt
cintay-0.1.dist-info/RECORD
